{
    "domain": "cdnpsh.com",
    "owner": {},
    "source": [
        "DuckDuckGo-DE"
    ],
    "prevalence": 0.000201,
    "sites": 2,
    "subdomains": [
        "pfeed"
    ],
    "cnames": [],
    "fingerprinting": 0,
    "resources": [
        {
            "rule": "cdnpsh\\.com\\/ps\\/config\\.js",
            "cookies": 0.000201,
            "fingerprinting": 0,
            "subdomains": [
                "pfeed"
            ],
            "apis": {},
            "sites": 2,
            "prevalence": 0.000201,
            "cnames": [],
            "responseHashes": [
                "39ab43d2c92eea10c3f21f346f4a137987f99da1efd496ddd3f132d166244e3d"
            ],
            "type": "Script",
            "firstPartyCookies": {},
            "firstPartyCookiesSent": {},
            "exampleSites": [
                "sexystars.online",
                "nacktefoto.com"
            ]
        }
    ],
    "categories": [],
    "performance": {},
    "cookies": 0.000201,
    "topInitiators": [
        {
            "domain": "nextpsh.top",
            "prevalence": 1
        }
    ],
    "types": {
        "Script": 2
    },
    "nameservers": [
        "ns1.dnsowl.com",
        "ns2.dnsowl.com",
        "ns3.dnsowl.com"
    ]
}