{
    "domain": "ebayadservices.com",
    "owner": {
        "name": "eBay, Inc.",
        "displayName": "eBay",
        "privacyPolicy": "https://pages.ebay.com/help/policies/privacy-policy.html",
        "url": "http://ebay.com"
    },
    "source": [
        "DuckDuckGo-DE"
    ],
    "prevalence": 0.0011,
    "sites": 11,
    "subdomains": [
        "www"
    ],
    "cnames": [],
    "fingerprinting": 1,
    "resources": [
        {
            "rule": "ebayadservices\\.com\\/marketingtracking\\/v1\\/ar",
            "cookies": 0.001,
            "fingerprinting": 0,
            "subdomains": [
                "www"
            ],
            "apis": {},
            "sites": 10,
            "prevalence": 0.001,
            "cnames": [],
            "responseHashes": [
                "f4eef8263281c0b26486637831251059757bc3fdc4c3a48045a8ef8646b36e8f"
            ],
            "type": "Fetch",
            "firstPartyCookies": {},
            "firstPartyCookiesSent": {},
            "exampleSites": [
                "din-formate.de",
                "fahrplan-bus-bahn.de",
                "www.anzugsmoment.de",
                "www.deinrechner.de",
                "www.din-formate.de",
                "www.pfarrei-deutschland.de",
                "www.recyclinghofwertstoffhof.de",
                "www.umrechnung-zoll-cm.de",
                "www.weltstahl.com",
                "zugfahrplande.com"
            ]
        }
    ],
    "categories": [],
    "performance": {},
    "cookies": 0.0011,
    "topInitiators": [
        {
            "domain": "doubleclick.net",
            "prevalence": 0.9285714285714286
        },
        {
            "domain": "googlesyndication.com",
            "prevalence": 0.07142857142857142
        }
    ],
    "types": {
        "Fetch": 10
    },
    "nameservers": [
        "dns1.p06.nsone.net",
        "dns2.p06.nsone.net",
        "dns3.p06.nsone.net",
        "dns4.p06.nsone.net",
        "ns01.ebaydns.com",
        "ns02.ebaydns.com",
        "ns03.ebaydns.com",
        "ns04.ebaydns.com"
    ]
}