{
    "domain": "juicebarads.com",
    "owner": {},
    "source": [
        "DuckDuckGo-US"
    ],
    "prevalence": 0.000034,
    "sites": 5,
    "subdomains": [
        "tags"
    ],
    "cnames": [],
    "fingerprinting": 1,
    "resources": [
        {
            "rule": "juicebarads\\.com\\/js\\/diariodocentrodomundo\\.js",
            "cookies": 0,
            "fingerprinting": 1,
            "subdomains": [
                "tags"
            ],
            "apis": {
                "window.innerWidth": 1,
                "Document.cookie getter": 1
            },
            "sites": 2,
            "prevalence": 0.0000136,
            "cnames": [],
            "responseHashes": [
                "98138b12e99eabbbc9df160cf5d8d3f056608a0b7d5c06985dee46294f56eaa8"
            ],
            "type": "Script",
            "firstPartyCookies": {},
            "firstPartyCookiesSent": {},
            "exampleSites": [
                "diariodocentrodomundo.com.br",
                "www.diariodocentrodomundo.com.br"
            ]
        }
    ],
    "categories": [],
    "performance": {},
    "cookies": 0,
    "topInitiators": [
        {
            "domain": "first party",
            "prevalence": 0.8
        },
        {
            "domain": "googletagmanager.com",
            "prevalence": 0.2
        }
    ],
    "types": {
        "Script": 2
    },
    "nameservers": [
        "hugh.ns.cloudflare.com",
        "brynne.ns.cloudflare.com"
    ]
}