{
    "domain": "ttaws.com",
    "owner": {},
    "source": [
        "DuckDuckGo-US"
    ],
    "prevalence": 0.0000136,
    "sites": 2,
    "subdomains": [
        "rt3api-prd"
    ],
    "cnames": [],
    "fingerprinting": 0,
    "resources": [
        {
            "rule": "ttaws\\.com\\/portals\\/portalDetails\\.json",
            "cookies": 0.0000136,
            "fingerprinting": 0,
            "subdomains": [
                "rt3api-prd"
            ],
            "apis": {},
            "sites": 2,
            "prevalence": 0.0000136,
            "cnames": [],
            "responseHashes": [
                "ac115515395c53665e39d01c72c0c15a7e265645910b11818d8fc3441e54e66c"
            ],
            "type": "XHR",
            "firstPartyCookies": {},
            "firstPartyCookiesSent": {},
            "exampleSites": [
                "circalasvegas.com",
                "www.circalasvegas.com"
            ]
        },
        {
            "rule": "ttaws\\.com\\/hotels\\/details\\.json",
            "cookies": 0.0000136,
            "fingerprinting": 0,
            "subdomains": [
                "rt3api-prd"
            ],
            "apis": {},
            "sites": 2,
            "prevalence": 0.0000136,
            "cnames": [],
            "responseHashes": [
                "b3618ec5a378f366e5420998ccb1193a50ad3bce726cecdbb76e80708d65351b"
            ],
            "type": "XHR",
            "firstPartyCookies": {},
            "firstPartyCookiesSent": {},
            "exampleSites": [
                "circalasvegas.com",
                "www.circalasvegas.com"
            ]
        },
        {
            "rule": "ttaws\\.com\\/hotels\\/special_rates\\.json",
            "cookies": 0.0000136,
            "fingerprinting": 0,
            "subdomains": [
                "rt3api-prd"
            ],
            "apis": {},
            "sites": 2,
            "prevalence": 0.0000136,
            "cnames": [],
            "responseHashes": [
                "5445a99cd35b1e2b1d913e2668c5a8dfb02d371edd938ab36cc4a8e73a6421d4"
            ],
            "type": "XHR",
            "firstPartyCookies": {},
            "firstPartyCookiesSent": {},
            "exampleSites": [
                "circalasvegas.com",
                "www.circalasvegas.com"
            ]
        },
        {
            "rule": "ttaws\\.com\\/hotels\\/rooms\\.json",
            "cookies": 0.0000136,
            "fingerprinting": 0,
            "subdomains": [
                "rt3api-prd"
            ],
            "apis": {},
            "sites": 2,
            "prevalence": 0.0000136,
            "cnames": [],
            "responseHashes": [
                "44b232b2bc288e694015f2308691b85bc9e3ca4fb7c9c832704cdefe9851da4d"
            ],
            "type": "XHR",
            "firstPartyCookies": {},
            "firstPartyCookiesSent": {},
            "exampleSites": [
                "circalasvegas.com",
                "www.circalasvegas.com"
            ]
        },
        {
            "rule": "ttaws\\.com\\/ext\\/recentBookings",
            "cookies": 0.0000136,
            "fingerprinting": 0,
            "subdomains": [
                "rt3api-prd"
            ],
            "apis": {},
            "sites": 2,
            "prevalence": 0.0000136,
            "cnames": [],
            "responseHashes": [
                "2ea77cccf3287209a95870fadb55e9119d4e155bcc4bb069c762beb17b99a508"
            ],
            "type": "XHR",
            "firstPartyCookies": {},
            "firstPartyCookiesSent": {},
            "exampleSites": [
                "circalasvegas.com",
                "www.circalasvegas.com"
            ]
        },
        {
            "rule": "ttaws\\.com\\/hotels\\/rate_calendar\\.json",
            "cookies": 0.0000136,
            "fingerprinting": 0,
            "subdomains": [
                "rt3api-prd"
            ],
            "apis": {},
            "sites": 2,
            "prevalence": 0.0000136,
            "cnames": [],
            "responseHashes": [
                "30e210e69f7b003db632c684b307f5ffe7c247752762b73c924fa112084183cb"
            ],
            "type": "XHR",
            "firstPartyCookies": {},
            "firstPartyCookiesSent": {},
            "exampleSites": [
                "circalasvegas.com",
                "www.circalasvegas.com"
            ]
        },
        {
            "rule": "ttaws\\.com\\/hotels\\/rateshopping\\.json",
            "cookies": 0.0000136,
            "fingerprinting": 0,
            "subdomains": [
                "rt3api-prd"
            ],
            "apis": {},
            "sites": 2,
            "prevalence": 0.0000136,
            "cnames": [],
            "responseHashes": [
                "e6acf7767cfbfd66692123b38a6eb58e9bc5330e05d85bef2b5b2d70b646a39a"
            ],
            "type": "XHR",
            "firstPartyCookies": {},
            "firstPartyCookiesSent": {},
            "exampleSites": [
                "circalasvegas.com",
                "www.circalasvegas.com"
            ]
        }
    ],
    "categories": [],
    "performance": {},
    "cookies": 0.0000136,
    "topInitiators": [
        {
            "domain": "traveltripper.io",
            "prevalence": 1
        }
    ],
    "types": {
        "XHR": 14
    },
    "nameservers": [
        "ns-94.awsdns-11.com",
        "ns-817.awsdns-38.net",
        "ns-1998.awsdns-57.co.uk",
        "ns-1268.awsdns-30.org"
    ]
}